playwright_stealth/__init__.py
playwright_stealth/core/__init__.py
playwright_stealth/core/_stealth_config.py
playwright_stealth/js/chrome.app.js
playwright_stealth/js/chrome.csi.js
playwright_stealth/js/chrome.load.times.js
playwright_stealth/js/chrome.plugin.js
playwright_stealth/js/chrome.runtime.js
playwright_stealth/js/generate.magic.arrays.js
playwright_stealth/js/iframe.contentWindow.js
playwright_stealth/js/media.codecs.js
playwright_stealth/js/navigator.hardwareConcurrency.js
playwright_stealth/js/navigator.languages.js
playwright_stealth/js/navigator.permissions.js
playwright_stealth/js/navigator.plugins.js
playwright_stealth/js/navigator.userAgent.js
playwright_stealth/js/navigator.vendor.js
playwright_stealth/js/navigator.webdriver.js
playwright_stealth/js/utils.js
playwright_stealth/js/webgl.vendor.js
playwright_stealth/js/window.outerdimensions.js
playwright_stealth/properties/__init__.py
playwright_stealth/properties/_header_properties.py
playwright_stealth/properties/_navigator_properties.py
playwright_stealth/properties/_properties.py
playwright_stealth/properties/_viewport_properties.py
playwright_stealth/properties/_webgl_properties.py
playwright_stealth/stealth.py
tf_playwright_stealth-1.1.3.dist-info/LICENSE
tf_playwright_stealth-1.1.3.dist-info/METADATA
tf_playwright_stealth-1.1.3.dist-info/WHEEL
tf_playwright_stealth-1.1.3.dist-info/RECORD
