Metadata-Version: 2.3
Name: tf-playwright-stealth
Version: 1.1.3
Summary: Makes playwright stealthy like a ninja!
License: MIT
Requires-Python: >=3.8,<4.0
Classifier: License :: OSI Approved :: MIT License
Classifier: Programming Language :: Python :: 3
Classifier: Programming Language :: Python :: 3.8
Classifier: Programming Language :: Python :: 3.9
Classifier: Programming Language :: Python :: 3.10
Classifier: Programming Language :: Python :: 3.11
Classifier: Programming Language :: Python :: 3.12
Classifier: Programming Language :: Python :: 3.13
Requires-Dist: fake-http-header (>=0.3.5,<0.4.0)
Requires-Dist: playwright (>=1,<2)
Project-URL: Homepage, https://www.agentql.com/
Project-URL: Repository, https://github.com/tinyfish-io/tf-playwright-stealth
